pyrasatest/__init__.py
pyrasatest/mock_db_session.py
pyrasatest/mock_model.py
pyrasatest/mock_pyramid_objects.py
pyrasatest/mock_query.py
pyrsatest-1.3.1.dist-info/LICENSE.txt
pyrsatest-1.3.1.dist-info/METADATA
pyrsatest-1.3.1.dist-info/WHEEL
pyrsatest-1.3.1.dist-info/top_level.txt
pyrsatest-1.3.1.dist-info/RECORD
