Metadata-Version: 2.1
Name: pyrsatest
Version: 1.3.1
Summary: Unit testing utilities for Pyramid applications
Home-page: https://github.com/paulosjd/pyrasatest
Author: Paul Davis
Author-email: pjdavis@gmx.com
License: MIT
Platform: UNKNOWN
Classifier: Programming Language :: Python :: 3
Classifier: License :: OSI Approved :: MIT License
Classifier: Operating System :: OS Independent
Requires-Python: >=3.6
Requires-Dist: pyramid
Requires-Dist: SQLAlchemy
